[
    {
        "id": 17870908837229743,
        "created_at": 1525595061,
        "text": "Niceeee! Greetings from other side of the world \ud83d\ude0a",
        "owner": {
            "id": "3597993366",
            "is_verified": false,
            "profile_pic_url": "https://scontent-xsp1-3.cdninstagram.com/v/t51.2885-19/s150x150/101340876_179519706724074_8850429911895113728_n.jpg?tp=1&_nc_ht=scontent-xsp1-3.cdninstagram.com&_nc_ohc=rW4eGGck0lEAX-HB7L6&ccb=7-4&oh=0e24db688958e9bcee94c722ee88e50d&oe=608D6AC5&_nc_sid=9fb510",
            "username": "shotwithmando"
        },
        "likes_count": 0,
        "answers": []
    },
    {
        "id": 17943490966046898,
        "created_at": 1525594498,
        "text": "#Scandinavian #scandinaviandesign #minimalist #minimalistdeco #mujiinspired #ilovesg #singaporebto #singaporeflats #organized #neat #clean #livingroom #visionblinds #curtain",
        "owner": {
            "id": "6759916903",
            "is_verified": false,
            "profile_pic_url": "https://scontent-xsp1-3.cdninstagram.com/v/t51.2885-19/s150x150/25024513_1518769984843497_3196571891569524736_n.jpg?tp=1&_nc_ht=scontent-xsp1-3.cdninstagram.com&_nc_ohc=nCclLyPBT4YAX9gnsor&ccb=7-4&oh=a600c407e614b8995592bf83eac5d4da&oe=608D404F&_nc_sid=9fb510",
            "username": "sarahlivingsg"
        },
        "likes_count": 0,
        "answers": []
    }
]