[
    {
        "id": 17850833440064589,
        "created_at": 1464436731,
        "text": "\ud83d\ude4c\ud83d\ude4c",
        "owner": {
            "id": "2353016267",
            "is_verified": false,
            "profile_pic_url": "https://scontent-xsp1-3.cdninstagram.com/v/t51.2885-19/s150x150/12725151_965789436823323_797331721_a.jpg?tp=1&_nc_ht=scontent-xsp1-3.cdninstagram.com&_nc_ohc=LIqHzMlMaqoAX-joQ10&ccb=7-4&oh=e89d07e03e23ee1ae24e42565c3cfc32&oe=608B9DAF&_nc_sid=9fb510",
            "username": "stendigcalendar"
        },
        "likes_count": 0,
        "answers": []
    }
]